{"nodes": [{"id": "c_users_quynh_graphify_repos_rtk_ai_rtk_src_core_truncate_rs", "label": "truncate.rs", "file_type": "code", "source_file": "C:\\Users\\quynh\\.graphify\\repos\\rtk-ai\\rtk\\src\\core\\truncate.rs", "source_location": "L1"}, {"id": "core_truncate_reduced", "label": "reduced()", "file_type": "code", "source_file": "C:\\Users\\quynh\\.graphify\\repos\\rtk-ai\\rtk\\src\\core\\truncate.rs", "source_location": "L15"}, {"id": "core_truncate_reduced_preserves_current_values", "label": "reduced_preserves_current_values()", "file_type": "code", "source_file": "C:\\Users\\quynh\\.graphify\\repos\\rtk-ai\\rtk\\src\\core\\truncate.rs", "source_location": "L28"}, {"id": "core_truncate_reduced_falls_back_to_cap_when_offset_too_large", "label": "reduced_falls_back_to_cap_when_offset_too_large()", "file_type": "code", "source_file": "C:\\Users\\quynh\\.graphify\\repos\\rtk-ai\\rtk\\src\\core\\truncate.rs", "source_location": "L34"}, {"id": "core_truncate_reduced_honors_zero_cap", "label": "reduced_honors_zero_cap()", "file_type": "code", "source_file": "C:\\Users\\quynh\\.graphify\\repos\\rtk-ai\\rtk\\src\\core\\truncate.rs", "source_location": "L40"}, {"id": "core_truncate_reduced_is_underflow_safe_across_all_inputs", "label": "reduced_is_underflow_safe_across_all_inputs()", "file_type": "code", "source_file": "C:\\Users\\quynh\\.graphify\\repos\\rtk-ai\\rtk\\src\\core\\truncate.rs", "source_location": "L48"}], "edges": [{"source": "c_users_quynh_graphify_repos_rtk_ai_rtk_src_core_truncate_rs", "target": "core_truncate_reduced", "relation": "contains", "confidence": "EXTRACTED", "source_file": "C:\\Users\\quynh\\.graphify\\repos\\rtk-ai\\rtk\\src\\core\\truncate.rs", "source_location": "L15", "weight": 1.0}, {"source": "c_users_quynh_graphify_repos_rtk_ai_rtk_src_core_truncate_rs", "target": "super", "relation": "imports_from", "confidence": "EXTRACTED", "source_file": "C:\\Users\\quynh\\.graphify\\repos\\rtk-ai\\rtk\\src\\core\\truncate.rs", "source_location": "L25", "weight": 1.0, "context": "import"}, {"source": "c_users_quynh_graphify_repos_rtk_ai_rtk_src_core_truncate_rs", "target": "core_truncate_reduced_preserves_current_values", "relation": "contains", "confidence": "EXTRACTED", "source_file": "C:\\Users\\quynh\\.graphify\\repos\\rtk-ai\\rtk\\src\\core\\truncate.rs", "source_location": "L28", "weight": 1.0}, {"source": "c_users_quynh_graphify_repos_rtk_ai_rtk_src_core_truncate_rs", "target": "core_truncate_reduced_falls_back_to_cap_when_offset_too_large", "relation": "contains", "confidence": "EXTRACTED", "source_file": "C:\\Users\\quynh\\.graphify\\repos\\rtk-ai\\rtk\\src\\core\\truncate.rs", "source_location": "L34", "weight": 1.0}, {"source": "c_users_quynh_graphify_repos_rtk_ai_rtk_src_core_truncate_rs", "target": "core_truncate_reduced_honors_zero_cap", "relation": "contains", "confidence": "EXTRACTED", "source_file": "C:\\Users\\quynh\\.graphify\\repos\\rtk-ai\\rtk\\src\\core\\truncate.rs", "source_location": "L40", "weight": 1.0}, {"source": "c_users_quynh_graphify_repos_rtk_ai_rtk_src_core_truncate_rs", "target": "core_truncate_reduced_is_underflow_safe_across_all_inputs", "relation": "contains", "confidence": "EXTRACTED", "source_file": "C:\\Users\\quynh\\.graphify\\repos\\rtk-ai\\rtk\\src\\core\\truncate.rs", "source_location": "L48", "weight": 1.0}, {"source": "core_truncate_reduced_is_underflow_safe_across_all_inputs", "target": "core_truncate_reduced", "relation": "calls", "context": "call", "confidence": "EXTRACTED", "source_file": "C:\\Users\\quynh\\.graphify\\repos\\rtk-ai\\rtk\\src\\core\\truncate.rs", "source_location": "L51", "weight": 1.0}], "raw_calls": []}